{
  "best_global_step": 150,
  "best_metric": 1.3409563302993774,
  "best_model_checkpoint": "./lora-legacy/checkpoint-150",
  "epoch": 1.7241379310344827,
  "eval_steps": 50,
  "global_step": 150,
  "is_hyper_param_search": false,
  "is_local_process_zero": true,
  "is_world_process_zero": true,
  "log_history": [
    {
      "entropy": 2.641289210319519,
      "epoch": 0.11494252873563218,
      "grad_norm": 2.109375,
      "learning_rate": 8.181818181818183e-05,
      "loss": 3.3367,
      "mean_token_accuracy": 0.4177286997437477,
      "num_tokens": 36824.0,
      "step": 10
    },
    {
      "entropy": 2.5190203338861465,
      "epoch": 0.22988505747126436,
      "grad_norm": 1.40625,
      "learning_rate": 0.00017272727272727275,
      "loss": 2.3555,
      "mean_token_accuracy": 0.5692525207996368,
      "num_tokens": 72860.0,
      "step": 20
    },
    {
      "entropy": 1.8733403265476227,
      "epoch": 0.3448275862068966,
      "grad_norm": 0.78125,
      "learning_rate": 0.0001998582695676762,
      "loss": 1.8524,
      "mean_token_accuracy": 0.6582474276423455,
      "num_tokens": 108652.0,
      "step": 30
    },
    {
      "entropy": 1.739985752105713,
      "epoch": 0.45977011494252873,
      "grad_norm": 0.91015625,
      "learning_rate": 0.00019916504666728533,
      "loss": 1.7305,
      "mean_token_accuracy": 0.6752587646245957,
      "num_tokens": 144339.0,
      "step": 40
    },
    {
      "entropy": 1.6468335509300231,
      "epoch": 0.5747126436781609,
      "grad_norm": 0.953125,
      "learning_rate": 0.0001978983034068459,
      "loss": 1.6411,
      "mean_token_accuracy": 0.6840872004628181,
      "num_tokens": 180103.0,
      "step": 50
    },
    {
      "epoch": 0.5747126436781609,
      "eval_entropy": 1.5894820659588544,
      "eval_loss": 1.6117327213287354,
      "eval_mean_token_accuracy": 0.6842267864789718,
      "eval_num_tokens": 180103.0,
      "eval_runtime": 47.0807,
      "eval_samples_per_second": 3.292,
      "eval_steps_per_second": 0.828,
      "step": 50
    },
    {
      "entropy": 1.6892937213182448,
      "epoch": 0.6896551724137931,
      "grad_norm": 1.71875,
      "learning_rate": 0.00019606536598722435,
      "loss": 1.647,
      "mean_token_accuracy": 0.678202460706234,
      "num_tokens": 216711.0,
      "step": 60
    },
    {
      "entropy": 1.5291203558444977,
      "epoch": 0.8045977011494253,
      "grad_norm": 0.97265625,
      "learning_rate": 0.00019367683518928226,
      "loss": 1.5449,
      "mean_token_accuracy": 0.6940833896398544,
      "num_tokens": 252830.0,
      "step": 70
    },
    {
      "entropy": 1.5305264979600905,
      "epoch": 0.9195402298850575,
      "grad_norm": 1.421875,
      "learning_rate": 0.0001907465250643337,
      "loss": 1.5136,
      "mean_token_accuracy": 0.6931246533989907,
      "num_tokens": 289101.0,
      "step": 80
    },
    {
      "entropy": 1.4902253925800324,
      "epoch": 1.0344827586206897,
      "grad_norm": 0.89453125,
      "learning_rate": 0.00018729138304067513,
      "loss": 1.4384,
      "mean_token_accuracy": 0.702695569396019,
      "num_tokens": 325440.0,
      "step": 90
    },
    {
      "entropy": 1.3891841769218445,
      "epoch": 1.1494252873563218,
      "grad_norm": 0.96484375,
      "learning_rate": 0.0001833313919082515,
      "loss": 1.3541,
      "mean_token_accuracy": 0.7088762164115906,
      "num_tokens": 362172.0,
      "step": 100
    },
    {
      "epoch": 1.1494252873563218,
      "eval_entropy": 1.35241655814342,
      "eval_loss": 1.4056541919708252,
      "eval_mean_token_accuracy": 0.7028392935410525,
      "eval_num_tokens": 362172.0,
      "eval_runtime": 46.9995,
      "eval_samples_per_second": 3.298,
      "eval_steps_per_second": 0.83,
      "step": 100
    },
    {
      "entropy": 1.3723428070545196,
      "epoch": 1.264367816091954,
      "grad_norm": 0.96484375,
      "learning_rate": 0.00017888945424832895,
      "loss": 1.3178,
      "mean_token_accuracy": 0.7167487546801568,
      "num_tokens": 398418.0,
      "step": 110
    },
    {
      "entropy": 1.3092512220144272,
      "epoch": 1.3793103448275863,
      "grad_norm": 1.0390625,
      "learning_rate": 0.00017399125997657477,
      "loss": 1.2874,
      "mean_token_accuracy": 0.7256275713443756,
      "num_tokens": 433756.0,
      "step": 120
    },
    {
      "entropy": 1.3515356630086899,
      "epoch": 1.4942528735632183,
      "grad_norm": 0.9765625,
      "learning_rate": 0.0001686651377656084,
      "loss": 1.3164,
      "mean_token_accuracy": 0.7148914039134979,
      "num_tokens": 470460.0,
      "step": 130
    },
    {
      "entropy": 1.3278012186288835,
      "epoch": 1.6091954022988506,
      "grad_norm": 1.0078125,
      "learning_rate": 0.00016294189120631954,
      "loss": 1.2887,
      "mean_token_accuracy": 0.7187238007783889,
      "num_tokens": 506640.0,
      "step": 140
    },
    {
      "entropy": 1.3249237149953843,
      "epoch": 1.7241379310344827,
      "grad_norm": 0.9765625,
      "learning_rate": 0.00015685462065551375,
      "loss": 1.2971,
      "mean_token_accuracy": 0.7223168358206749,
      "num_tokens": 542863.0,
      "step": 150
    },
    {
      "epoch": 1.7241379310344827,
      "eval_entropy": 1.3092454885825133,
      "eval_loss": 1.3409563302993774,
      "eval_mean_token_accuracy": 0.7118896383505601,
      "eval_num_tokens": 542863.0,
      "eval_runtime": 47.0711,
      "eval_samples_per_second": 3.293,
      "eval_steps_per_second": 0.829,
      "step": 150
    }
  ],
  "logging_steps": 10,
  "max_steps": 435,
  "num_input_tokens_seen": 0,
  "num_train_epochs": 5,
  "save_steps": 50,
  "stateful_callbacks": {
    "EarlyStoppingCallback": {
      "args": {
        "early_stopping_patience": 2,
        "early_stopping_threshold": 0.0
      },
      "attributes": {
        "early_stopping_patience_counter": 0
      }
    },
    "TrainerControl": {
      "args": {
        "should_epoch_stop": false,
        "should_evaluate": false,
        "should_log": false,
        "should_save": true,
        "should_training_stop": false
      },
      "attributes": {}
    }
  },
  "total_flos": 3857907769663488.0,
  "train_batch_size": 4,
  "trial_name": null,
  "trial_params": null
}
